healpix_convolution/__init__.py
healpix_convolution/convolution.py
healpix_convolution/distances.py
healpix_convolution/neighbours.py
healpix_convolution/padding.py
healpix_convolution/plotting.py
healpix_convolution/kernels/__init__.py
healpix_convolution/kernels/common.py
healpix_convolution/kernels/gaussian.py
healpix_convolution/tests/__init__.py
healpix_convolution/tests/test_convolution.py
healpix_convolution/tests/test_distances.py
healpix_convolution/tests/test_kernels.py
healpix_convolution/tests/test_neighbours.py
healpix_convolution/tests/test_padding.py
healpix_convolution/xarray/__init__.py
healpix_convolution/xarray/convolution.py
healpix_convolution/xarray/padding.py
healpix_convolution/xarray/utils.py
healpix_convolution/xarray/kernels/__init__.py
healpix_convolution/xarray/kernels/gaussian.py
healpix_convolution-0.1.2.dist-info/licenses/LICENSE
healpix_convolution-0.1.2.dist-info/METADATA
healpix_convolution-0.1.2.dist-info/WHEEL
healpix_convolution-0.1.2.dist-info/top_level.txt
healpix_convolution-0.1.2.dist-info/RECORD
